document_classifier/__init__.py
document_classifier/cnn.py
document_classifier-0.1.2.dist-info/LICENSE
document_classifier-0.1.2.dist-info/WHEEL
document_classifier-0.1.2.dist-info/METADATA
document_classifier-0.1.2.dist-info/RECORD
