Metadata-Version: 2.1
Name: document-classifier
Version: 0.1.2
Summary: A simple CNN for n-class classification of document images.
Home-page: https://github.com/sbischoff-ai/basic-document-classifier
License: MIT
Keywords: document,image,classification,deep,learning
Author: Silas Bischoff
Author-email: silas.bischoff@googlemail.com
Requires-Python: >=3.6,<4.0
Classifier: Development Status :: 4 - Beta
Classifier: Intended Audience :: Developers
Classifier: Intended Audience :: Financial and Insurance Industry
Classifier: Intended Audience :: Legal Industry
Classifier: Intended Audience :: Science/Research
Classifier: License :: OSI Approved :: MIT License
Classifier: Programming Language :: Python :: 3
Classifier: Programming Language :: Python :: 3.6
Classifier: Programming Language :: Python :: 3.7
Classifier: Topic :: Scientific/Engineering :: Artificial Intelligence
Classifier: Topic :: Scientific/Engineering :: Image Recognition
Classifier: Topic :: Software Development :: Libraries
Classifier: Topic :: Software Development :: Libraries :: Python Modules
Requires-Dist: keras (>=2.2,<3.0)
Requires-Dist: numpy (>=1.17,<2.0)
Requires-Dist: pillow (>=6.1,<7.0)
Requires-Dist: tensorflow-gpu (>=1.14,<2.0)
Project-URL: Repository, https://github.com/sbischoff-ai/basic-document-classifier
